eli_utils/__init__.py
eli_utils/_modidx.py
eli_utils/image.py
eli_utils/io.py
eli_utils/plotting.py
eli_utils/video.py
eli_utils/scripts/__init__.py
eli_utils/scripts/fiftyonify.py
eli_utils-0.0.21.dist-info/LICENSE
eli_utils-0.0.21.dist-info/METADATA
eli_utils-0.0.21.dist-info/WHEEL
eli_utils-0.0.21.dist-info/entry_points.txt
eli_utils-0.0.21.dist-info/top_level.txt
eli_utils-0.0.21.dist-info/RECORD
