Metadata-Version: 2.1
Name: eli-utils
Version: 0.0.21
Summary: Useful utilities I re-use in multiple projects
Home-page: https://github.com/elifriedman/eli_utils
Author: Eli Friedman
Author-email: 
License: Apache Software License 2.0
Keywords: nbdev jupyter notebook python
Classifier: Development Status :: 4 - Beta
Classifier: Intended Audience :: Developers
Classifier: Natural Language :: English
Classifier: Programming Language :: Python :: 3.7
Classifier: Programming Language :: Python :: 3.8
Classifier: Programming Language :: Python :: 3.9
Classifier: Programming Language :: Python :: 3.10
Classifier: License :: OSI Approved :: Apache Software License
Requires-Python: >=3.7
License-File: LICENSE
Requires-Dist: matplotlib
Requires-Dist: Pillow
Requires-Dist: numpy
Requires-Dist: opencv-python
Provides-Extra: dev
